StimRespFlow/DataIO.py
StimRespFlow/Metrics.py
StimRespFlow/__init__.py
StimRespFlow/outsideLibInterfaces.py
StimRespFlow/visualize.py
StimRespFlow/Analysis/Bootstrap.py
StimRespFlow/Analysis/CrossValidation.py
StimRespFlow/Analysis/MapReduce.py
StimRespFlow/Analysis/__init__.py
StimRespFlow/Analysis/temp.py
StimRespFlow/DataProcessing/SignalProcessing.py
StimRespFlow/DataProcessing/__init__.py
StimRespFlow/DataProcessing/stimop.py
StimRespFlow/DataProcessing/DeepLearning/Analyse.py
StimRespFlow/DataProcessing/DeepLearning/Factory.py
StimRespFlow/DataProcessing/DeepLearning/Metrics.py
StimRespFlow/DataProcessing/DeepLearning/Trainer.py
StimRespFlow/DataProcessing/DeepLearning/__init__.py
StimRespFlow/DataProcessing/DeepLearning/metrics_new.py
StimRespFlow/DataProcessing/DeepLearning/torchctx.py
StimRespFlow/DataProcessing/DeepLearning/torchctx_v2.py
StimRespFlow/DataProcessing/DeepLearning/trainer_new.py
StimRespFlow/DataStruct/Abstract.py
StimRespFlow/DataStruct/Array.py
StimRespFlow/DataStruct/DataSet.py
StimRespFlow/DataStruct/LabelData.py
StimRespFlow/DataStruct/ResultData.py
StimRespFlow/DataStruct/StimuliData.py
StimRespFlow/DataStruct/WaveData.py
StimRespFlow/DataStruct/__init__.py
StimRespFlow/Engines/OpTraceEngine.py
StimRespFlow/Engines/ResearchManage.py
StimRespFlow/Engines/StagesEngine.py
StimRespFlow/Engines/__init__.py
StimRespFlow/Helper/Cache.py
StimRespFlow/Helper/DataObjectTransform.py
StimRespFlow/Helper/MNEHelper.py
StimRespFlow/Helper/Protocol.py
StimRespFlow/Helper/StageControl.py
StimRespFlow/Helper/StudyManage.py
StimRespFlow/Helper/__init__.py
StimRespFlow/Preprocessing/ArtifactsRemoval.py
StimRespFlow/Preprocessing/__init__.py
stimrespflow-2.1.10.dist-info/licenses/LICENSE
stimrespflow-2.1.10.dist-info/METADATA
stimrespflow-2.1.10.dist-info/WHEEL
stimrespflow-2.1.10.dist-info/top_level.txt
stimrespflow-2.1.10.dist-info/RECORD
